CHANGES.rst
CONTRIBUTORS.rst
MANIFEST.in
README.rst
bootstrap.py
buildout.cfg
setup.py
travis.cfg
buildout.d/base.cfg
buildout.d/checkouts.cfg
buildout.d/development.cfg
buildout.d/jenkins.cfg
buildout.d/sources.cfg
buildout.d/versions.cfg
docs/LICENSE.GPL
docs/LICENSE.rst
src/collective/__init__.py
src/collective.local.contentrules.egg-info/PKG-INFO
src/collective.local.contentrules.egg-info/SOURCES.txt
src/collective.local.contentrules.egg-info/dependency_links.txt
src/collective.local.contentrules.egg-info/entry_points.txt
src/collective.local.contentrules.egg-info/namespace_packages.txt
src/collective.local.contentrules.egg-info/not-zip-safe
src/collective.local.contentrules.egg-info/requires.txt
src/collective.local.contentrules.egg-info/top_level.txt
src/collective/local/__init__.py
src/collective/local/contentrules/__init__.py
src/collective/local/contentrules/configure.zcml
src/collective/local/contentrules/setuphandlers.py~
src/collective/local/contentrules/stringinterp.py
src/collective/local/contentrules/testing.py
src/collective/local/contentrules/testing.py~
src/collective/local/contentrules/testing.zcml
src/collective/local/contentrules/locales/collective.local.contentrules.pot
src/collective/local/contentrules/locales/update.sh
src/collective/local/contentrules/locales/de/LC_MESSAGES/collective.local.contentrules.po
src/collective/local/contentrules/locales/es/LC_MESSAGES/collective.local.contentrules.po
src/collective/local/contentrules/locales/fr/LC_MESSAGES/collective.local.contentrules.po
src/collective/local/contentrules/locales/it/LC_MESSAGES/collective.local.contentrules.po
src/collective/local/contentrules/locales/pt/LC_MESSAGES/collective.local.contentrules.po
src/collective/local/contentrules/tests/__init__.py
src/collective/local/contentrules/tests/test_stringinterp.py