Metadata-Version: 1.1
Name: collective.local.contentrules
Version: 1.0rc1
Summary: Adds string interpolators to get emails of the collaborators on a document.
Home-page: http://pypi.python.org/pypi/collective.local.contentrules
Author: Thomas Desvenain
Author-email: thomasdesvenain@ecreall.com
License: GPL
Keywords: contentrules,workspace
Platform: UNKNOWN
Classifier: Environment :: Web Environment
Classifier: Framework :: Plone
Classifier: Framework :: Plone :: 4.3
Classifier: Programming Language :: Python
Classifier: Programming Language :: Python :: 2.7
